setup.py
helpgen/__init__.py
helpgen/decorators.py
helpgen/parser.py
helpgen.egg-info/PKG-INFO
helpgen.egg-info/SOURCES.txt
helpgen.egg-info/dependency_links.txt
helpgen.egg-info/not-zip-safe
helpgen.egg-info/top_level.txt