Metadata-Version: 1.0
Name: helpgen
Version: 0.1
Summary: Argparse frontend library to help making software
Home-page: https://github.com/bougie/helpgen
Author: David Hymonnet
Author-email: bougie@appartland.eu
License: BSD
Platform: UNKNOWN
